{
  "ComponentIndexes": {},
  "ControlUniqueIds": {
    "App": 1,
    "Background Music": 322,
    "Button2": 292,
    "Button3": 86,
    "Button4": 289,
    "Button4_1": 283,
    "Button4_2": 320,
    "Button6": 241,
    "Button6_1": 150,
    "Button6_10": 239,
    "Button6_11": 300,
    "Button6_12": 374,
    "Button6_13": 375,
    "Button6_14": 376,
    "Button6_15": 377,
    "Button6_16": 378,
    "Button6_17": 379,
    "Button6_18": 380,
    "Button6_19": 381,
    "Button6_2": 43,
    "Button6_20": 382,
    "Button6_21": 383,
    "Button6_3": 46,
    "Button6_4": 51,
    "Button6_5": 54,
    "Button6_6": 59,
    "Button6_7": 62,
    "Button6_8": 278,
    "Button6_9": 95,
    "Chatbot": 269,
    "Circle1": 290,
    "Circle1_1": 288,
    "Circle1_2": 293,
    "Circle1_3": 291,
    "Circle1_4": 68,
    "Circle1_5": 40,
    "Circle1_6": 284,
    "Circle1_7": 282,
    "Circle1_8": 321,
    "Circle1_9": 319,
    "Circle2": 75,
    "Circle2_1": 56,
    "Circle3": 246,
    "Circle3_1": 201,
    "Circle3_2": 260,
    "Circle3_3": 160,
    "Circle3_4": 175,
    "Circle3_5": 188,
    "Circle4": 267,
    "Circle4_1": 195,
    "Circle4_2": 208,
    "Circle4_3": 170,
    "Circle4_4": 182,
    "Circle4_5": 254,
    "Circle4_6": 88,
    "Circle4_7": 90,
    "Circle4_8": 92,
    "Emotions_1": 78,
    "Icon1": 99,
    "Icon1_1": 100,
    "Icon1_10": 109,
    "Icon1_11": 112,
    "Icon1_12": 113,
    "Icon1_13": 115,
    "Icon1_14": 114,
    "Icon1_15": 116,
    "Icon1_16": 117,
    "Icon1_17": 118,
    "Icon1_18": 119,
    "Icon1_19": 120,
    "Icon1_2": 102,
    "Icon1_20": 121,
    "Icon1_21": 122,
    "Icon1_22": 125,
    "Icon1_23": 126,
    "Icon1_24": 128,
    "Icon1_25": 127,
    "Icon1_26": 129,
    "Icon1_27": 130,
    "Icon1_28": 131,
    "Icon1_29": 132,
    "Icon1_3": 101,
    "Icon1_30": 133,
    "Icon1_31": 134,
    "Icon1_32": 135,
    "Icon1_33": 138,
    "Icon1_34": 139,
    "Icon1_35": 141,
    "Icon1_36": 140,
    "Icon1_37": 142,
    "Icon1_38": 143,
    "Icon1_39": 144,
    "Icon1_4": 103,
    "Icon1_40": 145,
    "Icon1_41": 146,
    "Icon1_42": 147,
    "Icon1_43": 148,
    "Icon1_44": 215,
    "Icon1_45": 216,
    "Icon1_46": 218,
    "Icon1_47": 217,
    "Icon1_48": 219,
    "Icon1_49": 220,
    "Icon1_5": 104,
    "Icon1_50": 221,
    "Icon1_51": 222,
    "Icon1_52": 223,
    "Icon1_53": 224,
    "Icon1_54": 225,
    "Icon1_55": 228,
    "Icon1_56": 229,
    "Icon1_57": 231,
    "Icon1_58": 230,
    "Icon1_59": 232,
    "Icon1_6": 105,
    "Icon1_60": 233,
    "Icon1_61": 234,
    "Icon1_62": 235,
    "Icon1_63": 236,
    "Icon1_64": 237,
    "Icon1_65": 238,
    "Icon1_7": 106,
    "Icon1_8": 107,
    "Icon1_9": 108,
    "Icon2_2": 161,
    "Icon3": 65,
    "Icon5": 257,
    "Icon5_1": 185,
    "Icon5_10": 330,
    "Icon5_11": 331,
    "Icon5_12": 336,
    "Icon5_13": 337,
    "Icon5_14": 338,
    "Icon5_2": 198,
    "Icon5_3": 157,
    "Icon5_4": 172,
    "Icon5_5": 243,
    "Icon5_6": 273,
    "Icon5_7": 317,
    "Icon5_8": 344,
    "Icon5_9": 16,
    "Icon6": 277,
    "Icon7": 276,
    "Icon8": 301,
    "Icon9": 66,
    "Image1": 287,
    "Image10": 286,
    "Image11": 335,
    "Image11_1": 187,
    "Image12_10": 266,
    "Image12_11": 194,
    "Image12_12": 168,
    "Image12_13": 181,
    "Image12_14": 252,
    "Image12_7": 200,
    "Image12_9": 206,
    "Image13_1": 245,
    "Image13_10": 209,
    "Image13_11": 183,
    "Image13_12": 255,
    "Image13_13": 253,
    "Image13_6": 268,
    "Image13_7": 169,
    "Image13_9": 196,
    "Image15": 343,
    "Image15_10": 207,
    "Image15_11": 178,
    "Image15_12": 251,
    "Image15_5": 264,
    "Image15_6": 166,
    "Image15_7": 174,
    "Image15_9": 193,
    "Image16": 274,
    "Image17": 345,
    "Image17_1": 363,
    "Image17_2": 364,
    "Image17_3": 365,
    "Image17_4": 370,
    "Image19": 350,
    "Image19_1": 358,
    "Image19_2": 361,
    "Image19_3": 369,
    "Image21": 281,
    "Image22": 352,
    "Image24": 18,
    "Image24_1": 4,
    "Image25": 22,
    "Image25_1": 9,
    "Image26": 23,
    "Image26_1": 10,
    "Image27": 24,
    "Image27_1": 11,
    "Image29": 355,
    "Image29_1": 360,
    "Image29_2": 362,
    "Image29_3": 372,
    "Image3": 67,
    "Image3_1": 94,
    "Image3_2": 153,
    "Image3_3": 211,
    "Image3_4": 39,
    "Image3_5": 366,
    "Image3_6": 367,
    "Image3_7": 368,
    "Image3_8": 371,
    "Image4": 37,
    "Image5": 325,
    "Image5_2": 79,
    "Image6": 38,
    "Image6_6": 87,
    "Image6_7": 89,
    "Image6_8": 91,
    "Image7": 328,
    "Image7_10": 204,
    "Image7_11": 165,
    "Image7_12": 179,
    "Image7_13": 249,
    "Image7_7": 263,
    "Image7_8": 259,
    "Image7_9": 192,
    "Image8_10": 203,
    "Image8_11": 177,
    "Image8_12": 248,
    "Image8_5": 262,
    "Image8_6": 164,
    "Image8_7": 159,
    "Image8_8": 163,
    "Image8_9": 190,
    "Image9": 334,
    "Image9_1": 348,
    "Image9_10": 250,
    "Image9_5": 265,
    "Image9_6": 167,
    "Image9_7": 191,
    "Image9_8": 205,
    "Image9_9": 180,
    "Label1": 82,
    "Label12": 152,
    "Label3": 80,
    "Label4": 84,
    "Label5": 244,
    "Label5_1": 247,
    "Label5_10": 226,
    "Label5_11": 240,
    "Label5_12": 173,
    "Label5_13": 158,
    "Label5_14": 258,
    "Label5_15": 261,
    "Label5_16": 202,
    "Label5_17": 189,
    "Label5_18": 176,
    "Label5_19": 162,
    "Label5_2": 199,
    "Label5_3": 186,
    "Label5_4": 123,
    "Label5_5": 136,
    "Label5_6": 97,
    "Label5_7": 110,
    "Label5_8": 149,
    "Label5_9": 213,
    "Label7": 41,
    "Label7_1": 96,
    "Label7_10": 304,
    "Label7_11": 307,
    "Label7_12": 306,
    "Label7_13": 308,
    "Label7_14": 310,
    "Label7_15": 311,
    "Label7_16": 312,
    "Label7_17": 314,
    "Label7_18": 315,
    "Label7_2": 212,
    "Label7_3": 275,
    "Label7_4": 280,
    "Label7_5": 295,
    "Label7_6": 296,
    "Label7_7": 297,
    "Label7_8": 299,
    "Label7_9": 303,
    "Label8": 69,
    "Label8_1": 70,
    "Label8_10": 55,
    "Label8_11": 60,
    "Label8_12": 318,
    "Label8_13": 34,
    "Label8_14": 20,
    "Label8_15": 21,
    "Label8_16": 25,
    "Label8_17": 26,
    "Label8_18": 27,
    "Label8_19": 7,
    "Label8_2": 72,
    "Label8_20": 8,
    "Label8_21": 12,
    "Label8_22": 13,
    "Label8_23": 14,
    "Label8_24": 329,
    "Label8_25": 17,
    "Label8_26": 5,
    "Label8_27": 326,
    "Label8_3": 71,
    "Label8_4": 74,
    "Label8_5": 77,
    "Label8_6": 44,
    "Label8_7": 47,
    "Label8_8": 50,
    "Label8_9": 49,
    "Portal Screen": 285,
    "Portal Screen_1": 93,
    "Portal Screen_2": 210,
    "Presentation Screen": 151,
    "Profile Screen_1": 63,
    "Profile Screen_2": 35,
    "Rectangle1_14": 45,
    "Rectangle1_15": 48,
    "Rectangle1_16": 52,
    "Rectangle1_17": 58,
    "Rectangle1_18": 61,
    "Rectangle1_3": 73,
    "Rectangle1_4": 76,
    "Rectangle1_5": 53,
    "Rectangle1_6": 57,
    "Rectangle1_7": 42,
    "Rectangle4": 64,
    "Rectangle4_1": 36,
    "Schedule_1": 272,
    "Schedule_2": 279,
    "Schedule_3": 294,
    "Schedule_4": 302,
    "Special Break_1": 316,
    "Special Break_2": 15,
    "Special Break_3": 3,
    "Special Break_4": 28,
    "Special Break_5": 29,
    "Special Break_6": 30,
    "Special Break_7": 31,
    "Special Break_8": 32,
    "Special Break_9": 33,
    "TextInput5_10": 214,
    "TextInput5_11": 227,
    "TextInput5_12": 298,
    "TextInput5_4": 98,
    "TextInput5_5": 373,
    "TextInput5_7": 111,
    "TextInput5_8": 124,
    "TextInput5_9": 137,
    "To relax your mind_1_Serene": 256,
    "To relax your mind_2_Anger": 184,
    "To relax your mind_3_Surprised": 197,
    "To relax your mind_4_Happy": 156,
    "To relax your mind_5_Insecure": 171,
    "To relax your mind_6_Sad": 242,
    "Toggle1": 305,
    "Toggle1_1": 309,
    "Toggle1_2": 313,
    "Toggle2": 19,
    "Toggle2_1": 327,
    "Toggle2_2": 6,
    "txtdate": 83,
    "txtHowdoyoufeel": 85,
    "txtName": 81
  },
  "FunctionParamsInvariantScripts": {},
  "FunctionParamsInvariantScriptsOnInstances": {},
  "HeaderLastSavedDateTimeUTC": "06/24/2022 08:30:09",
  "IsLegacyComponentAllowGlobalScopeCase": false,
  "LocalConnectionIDReferences": {
    "394f40cd-0605-4e30-af59-02b4af538f70": "\"/providers/microsoft.powerapps/apis/shared_sharepointonline/connections/62fb90473d634284976171189472d5b6\"",
    "750d4eeb-33af-43a0-8422-9754a4a64f42": "\"/providers/microsoft.powerapps/apis/shared_microsoftflowforadmins/connections/90816e85cd934899a9663d16db3dee34\"",
    "b0746622-a857-457e-9ac3-194f502f2e1b": "\"/providers/microsoft.powerapps/apis/shared_logicflows/connections/d1582e47247d4287978b6008fedad7a8\"",
    "c09fc639-7976-45da-a3cb-c01fae4cba1b": "\"/providers/microsoft.powerapps/apis/shared_office365/connections/shared-office365-e854e7d6-f942-4ff4-a3b1-55a9061af0cb\"",
    "fc0d165a-95ac-46b5-9629-96af3c3bfcef": "\"/providers/microsoft.powerapps/apis/shared_logicflows/connections/2a0f3b66216546ac8e1bc85e8045eccf\""
  },
  "LocalDatabaseReferencesAsEmpty": false,
  "LocalResourceFileNames": {
    "1": "0001.png",
    "10": "0003.png",
    "10-removebg-preview": "0002.png",
    "11": "0004.png",
    "12": "0006.png",
    "12-removebg-preview": "0005.png",
    "13": "0008.png",
    "13-removebg-preview": "0007.png",
    "14": "0010.png",
    "14-removebg-preview": "0009.png",
    "15": "0012.png",
    "15-removebg-preview": "0011.png",
    "17": "0013.png",
    "19": "0014.png",
    "2": "0015.png",
    "2_1": "a88d8729-94c4-4d49-b99e-746fb6cfe0b2.png",
    "22": "c63c9d4c-31ec-4eb3-b85d-a37485f6cb58.png",
    "22_1": "ed21362e-9d07-49e7-8e64-43dc357e759b.png",
    "23": "6a27f943-007f-4747-a629-79988c1f4c03.png",
    "23_1": "cd2455ee-ccec-47ce-83c8-73df0b1decd4.png",
    "23_2": "b8cc1d63-7316-40b8-8f5d-43f5ed3f6e0e.png",
    "24": "c15650de-16cb-46ba-8861-9ac7277acdb0.png",
    "24_1": "124ecede-20f9-4418-b691-8e5178418454.png",
    "24_2": "76c2b8dc-2dc4-455d-8df6-0b56c2c4de67.png",
    "25": "48c90e62-3aab-449c-9fe2-5113c52e6dd2.png",
    "26": "0d39b3d2-286c-4785-afee-cf0cc0012091.png",
    "26_1": "b57b7755-fd5a-4458-9919-2c241ac64bad.png",
    "26_2": "4684d8d3-5d58-4978-aad4-cfc5412c31ae.png",
    "27": "05ca11e9-5fcf-42aa-853c-8f619e1a1685.png",
    "27_1": "d8e4c971-4407-4faf-9c2d-4488d906557c.png",
    "28": "6bf18add-1726-4ca2-a424-bc3d99d9e7f5.png",
    "3": "0016.png",
    "3_1": "debdfcc4-a903-4aae-9e33-659946f74e29.png",
    "4": "0017.png",
    "4_1": "2e1a5acd-83e5-413d-a6c0-985db6ddee61.png",
    "4_2": "4daeac05-1cce-4f42-a090-817ae3725be3.png",
    "5": "40e2a985-ac3b-47ac-bfb7-2222be4f4c64.png",
    "5_1": "e00f81a7-0192-48f7-a0e7-eb51e9b0c283.png",
    "6": "0018.png",
    "6_1": "76cafd28-65e6-47c2-b9a7-45f1a7888835.png",
    "6_2": "09c8a5f3-e846-413c-9839-8ea66e8c5b67.png",
    "7": "0019.png",
    "8": "0020.png",
    "9": "0021.png",
    "Acreditación Project": "0026.png",
    "Acreditación Project (1)": "0023.png",
    "Acreditación Project (3)": "0024.png",
    "Acreditación Project (4)": "0025.png",
    "Añadir un subtítulo": "0022.jpg",
    "Anie Adame": "0029.png",
    "Anie Adame (1)": "0027.png",
    "Anie Adame (1)_1": "0028.png",
    "Anie Adame (10)": "51a3d7b0-9ead-4631-b262-24aa29f3c879.png",
    "Anie Adame (11)": "6e9c70ce-34d9-4d9f-90f2-0744696cbdf0.png",
    "Anie Adame (12)": "a2b33d68-267b-4eca-b3e7-ae6d01ad4265.png",
    "Anie Adame (12)_1": "33c91d21-b0f3-43f2-b41c-32ab84f18525.png",
    "Anie Adame (12)_2": "f5c6335b-e7ab-4a2f-8182-407fbe53be1e.png",
    "Anie Adame (13)": "bfe38494-ee4e-461b-a11b-f79e7fe31642.png",
    "Anie Adame (13)_1": "4ddc87ee-7e79-4fe8-8341-5c783afae2a5.png",
    "Anie Adame (14)": "618a924d-a515-4db6-8e55-bc9ce146cc61.png",
    "Anie Adame (14)_1": "3ccbe5a2-3d21-41bf-80e0-4b6d21fd47cf.png",
    "Anie Adame (15)": "758e31b5-5fcd-44a7-8c4d-ac9cdaa1a59f.png",
    "Anie Adame (15)_1": "a7e3d411-36d9-4dce-aca0-0c12678c26a4.png",
    "Anie Adame (16)": "2ddd17a0-15cb-4f28-8d83-bde349a53454.png",
    "Anie Adame (5)": "93d69d76-a1b8-44e0-9c9a-d009f6d41f2c.png",
    "Anie Adame (6)": "35eb6dff-9031-4eff-bafc-e0364c79f104.png",
    "Anie Adame (7)": "5f337746-8111-448b-8f78-c88ccd59ffc7.png",
    "Anie Adame (8)": "ebf33901-066e-4780-b837-3891ba6a7308.png",
    "Anie Adame (8)_1": "19bebd3e-790b-44a6-ba74-655fc518fc8f.png",
    "Anie Adame (9)": "be310e24-d726-4fa9-8bdf-79ef1517ecd1.png",
    "Avatar Power apps": "0030.png",
    "chat": "0031.png",
    "Cielo_nublado": "0032.jpg",
    "difuminado 2": "0033.jpg",
    "Diseño sin título (1)": "871675c1-5614-4827-b2f1-5e9d06381a62.png",
    "Diseño sin título (2)": "b773bfdf-abac-44c4-879c-b735bb5cbbf2.png",
    "Diseño sin título (3)": "7ffbf2ee-22a5-4ce2-9df4-9728ec408e92.png",
    "Diseño sin título (3)_1": "8bae8a98-64c4-4353-a8f0-6a11805d78fa.png",
    "Diseño sin título (4)": "04d4c893-af18-4e56-a177-d739ab90d002.png",
    "Diseño sin título (5)": "cc77b009-bca6-4ef5-90ab-8241d88ee0fa.png",
    "Diseño sin título (6)": "247e6579-5783-44ac-b509-f144a5725630.png",
    "Diseño sin título (7)": "48aeccc7-1271-47ce-a836-b5968bd116b3.png",
    "Diseño sin título (8)": "7082b406-b6a1-4a79-aac4-5576465baa5c.png",
    "download": "0034.png",
    "fondo": "0035.png",
    "Logo Acrediitación Azul": "0036.png",
    "Logo Acreditación": "0037.png",
    "master": "0038.jpg",
    "Negro Sencillo Evento Deportivo Póster": "0039.jpg",
    "Notification Message": "0040.png",
    "Zulu (2)": "aa5f9d07-a38b-4936-9336-f8806db7bf22.png",
    "Zulu (3)": "7eda78e8-19e5-4c1e-a87b-79bf0bdcb9a3.png",
    "Zulu (4)": "434b5a0c-6423-4d21-a2ce-24dbd6924bb3.png",
    "Zulu (5)": "aa385be8-df8b-43cd-b17d-3ae36d860b3d.png",
    "Zulu (6)": "0dd37896-81e3-4aa7-9828-997514ec5898.png",
    "Zulu (7)": "8b9ca84f-a483-402e-b6a6-465e156757d3.png",
    "Zulu (7)_1": "12197505-9e52-4254-b4b1-af307aa4d90f.png",
    "Zulu (8)": "3d59f941-82d2-4d30-9d9b-414188189715.png",
    "Zulu (8)_1": "87908c35-547f-43a4-bb6d-41fe39200db9.png",
    "Zulu (9)": "e34970a4-4d5a-4f63-9eaf-e6d6e7a7e256.png",
    "Zulu (9)_1": "7564b77a-f0f0-4c56-b1a1-bff5d6c8989d.png",
    "Zulu_presentación-removebg-preview": "0041.png"
  },
  "LocalResourceRootPaths": {
    "1": "https://docserverpwaprodeus.blob.core.windows.net/fbef9da9-667f-472c-979a-d1a1cc45d97b-1/resource/Assets0Images00001.png?sv=2017-04-17&sr=b&sig=0uwztaWuaC528JhKTDpnu68gr%2B0X3aO2u1mOXF415Ag%3D&spr=https&se=2022-06-25T05%3A06%3A26Z&sp=r",
    "10": "https://docserverpwaprodeus.blob.core.windows.net/fbef9da9-667f-472c-979a-d1a1cc45d97b-1/resource/Assets0Images00003.png?sv=2017-04-17&sr=b&sig=CtNtYorS7yeKjb42%2BLkn3O%2BdJaOqeKzP1AIlsKYlhww%3D&spr=https&se=2022-06-25T05%3A06%3A26Z&sp=r",
    "10-removebg-preview": "https://docserverpwaprodeus.blob.core.windows.net/fbef9da9-667f-472c-979a-d1a1cc45d97b-1/resource/Assets0Images00002.png?sv=2017-04-17&sr=b&sig=KPbgOiwEaKxbVonsjs4%2FsO043fULB539mLq1XAnBpbI%3D&spr=https&se=2022-06-25T05%3A06%3A26Z&sp=r",
    "11": "https://docserverpwaprodeus.blob.core.windows.net/fbef9da9-667f-472c-979a-d1a1cc45d97b-1/resource/Assets0Images00004.png?sv=2017-04-17&sr=b&sig=qYk0iAe%2BO9q7RZP6DIbEALoyCc8%2Fl81Zdb5D5vkgTNE%3D&spr=https&se=2022-06-25T05%3A06%3A26Z&sp=r",
    "12": "https://docserverpwaprodeus.blob.core.windows.net/fbef9da9-667f-472c-979a-d1a1cc45d97b-1/resource/Assets0Images00006.png?sv=2017-04-17&sr=b&sig=xOJtnwFtYnX9xn%2B%2FX4GRrJMmzhGIfAeFZClWqM4ki8c%3D&spr=https&se=2022-06-25T05%3A06%3A26Z&sp=r",
    "12-removebg-preview": "https://docserverpwaprodeus.blob.core.windows.net/fbef9da9-667f-472c-979a-d1a1cc45d97b-1/resource/Assets0Images00005.png?sv=2017-04-17&sr=b&sig=RQLDLwZIJfimWPBkNNp9kgsXpjej3TNGm6b2lDgRNos%3D&spr=https&se=2022-06-25T05%3A06%3A26Z&sp=r",
    "13": "https://docserverpwaprodeus.blob.core.windows.net/fbef9da9-667f-472c-979a-d1a1cc45d97b-1/resource/Assets0Images00008.png?sv=2017-04-17&sr=b&sig=mVO99xOL6ah7xFkkW2%2Bh3pCdrerWPot7ooaX2HUzV7k%3D&spr=https&se=2022-06-25T05%3A06%3A26Z&sp=r",
    "13-removebg-preview": "https://docserverpwaprodeus.blob.core.windows.net/fbef9da9-667f-472c-979a-d1a1cc45d97b-1/resource/Assets0Images00007.png?sv=2017-04-17&sr=b&sig=aDZ4hVTItM1%2BFh%2FelYQY8nhIUz1uyr43366GpcHS5a4%3D&spr=https&se=2022-06-25T05%3A06%3A26Z&sp=r",
    "14": "https://docserverpwaprodeus.blob.core.windows.net/fbef9da9-667f-472c-979a-d1a1cc45d97b-1/resource/Assets0Images00010.png?sv=2017-04-17&sr=b&sig=chpTD5DiK9tH6H8hOdeujW85m5My72NZdvm5Rrfzw0U%3D&spr=https&se=2022-06-25T05%3A06%3A26Z&sp=r",
    "14-removebg-preview": "https://docserverpwaprodeus.blob.core.windows.net/fbef9da9-667f-472c-979a-d1a1cc45d97b-1/resource/Assets0Images00009.png?sv=2017-04-17&sr=b&sig=2le%2FCv3iFdaumU3vzfR6Ts1qp4gbmRO6DLflI8bZRr8%3D&spr=https&se=2022-06-25T05%3A06%3A26Z&sp=r",
    "15": "https://docserverpwaprodeus.blob.core.windows.net/fbef9da9-667f-472c-979a-d1a1cc45d97b-1/resource/Assets0Images00012.png?sv=2017-04-17&sr=b&sig=sX%2Bi9%2FoDFhksi3qvzlCbEo3p8bcp5d5VfUjjwc6Fl9s%3D&spr=https&se=2022-06-25T05%3A06%3A26Z&sp=r",
    "15-removebg-preview": "https://docserverpwaprodeus.blob.core.windows.net/fbef9da9-667f-472c-979a-d1a1cc45d97b-1/resource/Assets0Images00011.png?sv=2017-04-17&sr=b&sig=HFYSlNA4nt4Yc2YG5q7vn2Abv%2Be%2FRBCE%2F4T4OvKk%2Fzs%3D&spr=https&se=2022-06-25T05%3A06%3A26Z&sp=r",
    "17": "https://docserverpwaprodeus.blob.core.windows.net/fbef9da9-667f-472c-979a-d1a1cc45d97b-1/resource/Assets0Images00013.png?sv=2017-04-17&sr=b&sig=NW%2FT2xf5hGIbLhiNpvl0NfdEWK4GSONAdiWh7L51GPk%3D&spr=https&se=2022-06-25T05%3A06%3A26Z&sp=r",
    "19": "https://docserverpwaprodeus.blob.core.windows.net/fbef9da9-667f-472c-979a-d1a1cc45d97b-1/resource/Assets0Images00014.png?sv=2017-04-17&sr=b&sig=fWuAQecuPzBElXKK%2FNSunvgeVmut0629xVyXxHX7Dr0%3D&spr=https&se=2022-06-25T05%3A06%3A26Z&sp=r",
    "2": "https://docserverpwaprodeus.blob.core.windows.net/fbef9da9-667f-472c-979a-d1a1cc45d97b-1/resource/Assets0Images00015.png?sv=2017-04-17&sr=b&sig=zFx5sZ0EPHZ3WUmI4d92rJ6Nfh8nHWgv%2FbVpTpPk%2FJ4%3D&spr=https&se=2022-06-25T05%3A06%3A26Z&sp=r",
    "2_1": "https://docserverpwaprodeus.blob.core.windows.net/fbef9da9-667f-472c-979a-d1a1cc45d97b-1/resource/Assets0Images0a88d8729-94c4-4d49-b99e-746fb6cfe0b2.png?sv=2017-04-17&sr=b&sig=tlEhcFCIfmvBsBqEJCII2mHVHoYauw4HslJh%2BUm7KP4%3D&spr=https&se=2022-06-25T05%3A06%3A26Z&sp=r",
    "22": "https://docserverpwaprodeus.blob.core.windows.net/fbef9da9-667f-472c-979a-d1a1cc45d97b-1/resource/Assets0Images0c63c9d4c-31ec-4eb3-b85d-a37485f6cb58.png?sv=2017-04-17&sr=b&sig=7XV3vfE%2FWqxkDVI062kSYSgd%2B18jKOhWwgff6P6y510%3D&spr=https&se=2022-06-25T05%3A06%3A26Z&sp=r",
    "22_1": "https://docserverpwaprodeus.blob.core.windows.net/fbef9da9-667f-472c-979a-d1a1cc45d97b-1/resource/Assets0Images0ed21362e-9d07-49e7-8e64-43dc357e759b.png?sv=2017-04-17&sr=b&sig=95aWAPTKAimM44kTeQSjQOGzMN5YH64EtXiZQkcprJM%3D&spr=https&se=2022-06-25T05%3A06%3A26Z&sp=r",
    "23": "https://docserverpwaprodeus.blob.core.windows.net/fbef9da9-667f-472c-979a-d1a1cc45d97b-1/resource/Assets0Images06a27f943-007f-4747-a629-79988c1f4c03.png?sv=2017-04-17&sr=b&sig=KI9hEQu8IFGz6%2FURc1O4Q5VmVGT0L3Newqh1%2B8A9xB4%3D&spr=https&se=2022-06-25T05%3A06%3A26Z&sp=r",
    "23_1": "https://docserverpwaprodeus.blob.core.windows.net/fbef9da9-667f-472c-979a-d1a1cc45d97b-1/resource/Assets0Images0cd2455ee-ccec-47ce-83c8-73df0b1decd4.png?sv=2017-04-17&sr=b&sig=3KizwO1h3cgur0NRvUVcsb5EQWgv4OFY0TDnOx9TxmA%3D&spr=https&se=2022-06-25T05%3A06%3A26Z&sp=r",
    "23_2": "https://docserverpwaprodeus.blob.core.windows.net/fbef9da9-667f-472c-979a-d1a1cc45d97b-1/resource/Assets0Images0b8cc1d63-7316-40b8-8f5d-43f5ed3f6e0e.png?sv=2017-04-17&sr=b&sig=8Cb0o0wKPAnUBIxU25XZl2N8SRSLGE0cPL8k9%2F6FpQs%3D&spr=https&se=2022-06-25T05%3A06%3A26Z&sp=r",
    "24": "https://docserverpwaprodeus.blob.core.windows.net/fbef9da9-667f-472c-979a-d1a1cc45d97b-1/resource/Assets0Images0c15650de-16cb-46ba-8861-9ac7277acdb0.png?sv=2017-04-17&sr=b&sig=zSCSbVs4URLESfI7E9dqmoqUYlppu6CBCTlMUPLrwt0%3D&spr=https&se=2022-06-25T05%3A06%3A26Z&sp=r",
    "24_1": "https://docserverpwaprodeus.blob.core.windows.net/fbef9da9-667f-472c-979a-d1a1cc45d97b-1/resource/Assets0Images0124ecede-20f9-4418-b691-8e5178418454.png?sv=2017-04-17&sr=b&sig=IF7SxGOqtzkIUSo9COiIxBw47QcCxMbezkrH2xmhw0Y%3D&spr=https&se=2022-06-25T05%3A06%3A26Z&sp=r",
    "24_2": "https://docserverpwaprodeus.blob.core.windows.net/fbef9da9-667f-472c-979a-d1a1cc45d97b-1/resource/Assets0Images076c2b8dc-2dc4-455d-8df6-0b56c2c4de67.png?sv=2017-04-17&sr=b&sig=uR8Zf04m8BaEi6WQRI7N9xGY4%2FsgiRhb1%2FE90EcNJto%3D&spr=https&se=2022-06-25T05%3A06%3A26Z&sp=r",
    "25": "https://docserverpwaprodeus.blob.core.windows.net/fbef9da9-667f-472c-979a-d1a1cc45d97b-1/resource/Assets0Images048c90e62-3aab-449c-9fe2-5113c52e6dd2.png?sv=2017-04-17&sr=b&sig=qDkFLpKK5ety2hc3z6dmRvh0QYWb5DTGMz65ck%2FNaSw%3D&spr=https&se=2022-06-25T05%3A06%3A26Z&sp=r",
    "26": "https://docserverpwaprodeus.blob.core.windows.net/fbef9da9-667f-472c-979a-d1a1cc45d97b-1/resource/Assets0Images00d39b3d2-286c-4785-afee-cf0cc0012091.png?sv=2017-04-17&sr=b&sig=ALiA17tBdz7hha0TQnWqdap4iixFf5oBcyTnLbvyhtw%3D&spr=https&se=2022-06-25T05%3A06%3A26Z&sp=r",
    "26_1": "https://docserverpwaprodeus.blob.core.windows.net/fbef9da9-667f-472c-979a-d1a1cc45d97b-1/resource/Assets0Images0b57b7755-fd5a-4458-9919-2c241ac64bad.png?sv=2017-04-17&sr=b&sig=vBZq1OsROKjPndKI44Otc44BPcE9uxLJJGPB1RFCA%2Bc%3D&spr=https&se=2022-06-25T05%3A06%3A26Z&sp=r",
    "26_2": "https://docserverpwaprodeus.blob.core.windows.net/fbef9da9-667f-472c-979a-d1a1cc45d97b-1/resource/Assets0Images04684d8d3-5d58-4978-aad4-cfc5412c31ae.png?sv=2017-04-17&sr=b&sig=LzfazdeOVY8QJMiqKe%2FXGzSA4unUDQKA1QuenaADQVE%3D&spr=https&se=2022-06-25T05%3A06%3A26Z&sp=r",
    "27": "https://docserverpwaprodeus.blob.core.windows.net/fbef9da9-667f-472c-979a-d1a1cc45d97b-1/resource/Assets0Images005ca11e9-5fcf-42aa-853c-8f619e1a1685.png?sv=2017-04-17&sr=b&sig=KGmAP600J4FqC0t3b5bCUFHH9DpQ0MFFaoWTjoKPTOM%3D&spr=https&se=2022-06-25T05%3A06%3A26Z&sp=r",
    "27_1": "https://docserverpwaprodeus.blob.core.windows.net/fbef9da9-667f-472c-979a-d1a1cc45d97b-1/resource/Assets0Images0d8e4c971-4407-4faf-9c2d-4488d906557c.png?sv=2017-04-17&sr=b&sig=QIeSlkJufN6DM45D22mLYlQFK9tmTunsn12QBljq61I%3D&spr=https&se=2022-06-25T05%3A06%3A26Z&sp=r",
    "28": "https://docserverpwaprodeus.blob.core.windows.net/fbef9da9-667f-472c-979a-d1a1cc45d97b-1/resource/Assets0Images06bf18add-1726-4ca2-a424-bc3d99d9e7f5.png?sv=2017-04-17&sr=b&sig=Y78zei7IzFRYrG0clBnqwmKTBa9%2FhccUqAbSEGrXrdg%3D&spr=https&se=2022-06-25T05%3A06%3A26Z&sp=r",
    "3": "https://docserverpwaprodeus.blob.core.windows.net/fbef9da9-667f-472c-979a-d1a1cc45d97b-1/resource/Assets0Images00016.png?sv=2017-04-17&sr=b&sig=xQgVyRYQQ1FCYF1N0HXH%2FW8gvCvHcagQJq77erCf6QM%3D&spr=https&se=2022-06-25T05%3A06%3A26Z&sp=r",
    "3_1": "https://docserverpwaprodeus.blob.core.windows.net/fbef9da9-667f-472c-979a-d1a1cc45d97b-1/resource/Assets0Images0debdfcc4-a903-4aae-9e33-659946f74e29.png?sv=2017-04-17&sr=b&sig=4QTKoSxMQxLq%2B%2BqnLGbCidrokWP5XcnRNyGBdzcmLqQ%3D&spr=https&se=2022-06-25T05%3A06%3A26Z&sp=r",
    "4": "https://docserverpwaprodeus.blob.core.windows.net/fbef9da9-667f-472c-979a-d1a1cc45d97b-1/resource/Assets0Images00017.png?sv=2017-04-17&sr=b&sig=k2JwXoGuvsJ2lETOeoQK7H7B3jC4hNVxd%2FlSDbyAQjM%3D&spr=https&se=2022-06-25T05%3A06%3A26Z&sp=r",
    "4_1": "https://docserverpwaprodeus.blob.core.windows.net/fbef9da9-667f-472c-979a-d1a1cc45d97b-1/resource/Assets0Images02e1a5acd-83e5-413d-a6c0-985db6ddee61.png?sv=2017-04-17&sr=b&sig=5R%2BmPA1P%2B5S53sqFh5oD7TB3ESbsPuutjiB2VDjEy3s%3D&spr=https&se=2022-06-25T05%3A06%3A26Z&sp=r",
    "4_2": "https://docserverpwaprodeus.blob.core.windows.net/fbef9da9-667f-472c-979a-d1a1cc45d97b-1/resource/Assets0Images04daeac05-1cce-4f42-a090-817ae3725be3.png?sv=2017-04-17&sr=b&sig=adorjn2qvqC3S7Gv%2FHWwR%2FdzgXctLzou9ts1C%2BzcFyM%3D&spr=https&se=2022-06-25T05%3A06%3A26Z&sp=r",
    "5": "https://docserverpwaprodeus.blob.core.windows.net/fbef9da9-667f-472c-979a-d1a1cc45d97b-1/resource/Assets0Images040e2a985-ac3b-47ac-bfb7-2222be4f4c64.png?sv=2017-04-17&sr=b&sig=md2rIVGdto7VdEloHfvVVVmMG7%2F31yXximcLSd1b%2FwA%3D&spr=https&se=2022-06-25T05%3A06%3A26Z&sp=r",
    "5_1": "https://docserverpwaprodeus.blob.core.windows.net/fbef9da9-667f-472c-979a-d1a1cc45d97b-1/resource/Assets0Images0e00f81a7-0192-48f7-a0e7-eb51e9b0c283.png?sv=2017-04-17&sr=b&sig=MjWJtGvszkOw1n7tQhlYfaAMsYwv5jdBhVxNKTyRjpc%3D&spr=https&se=2022-06-25T05%3A06%3A26Z&sp=r",
    "6": "https://docserverpwaprodeus.blob.core.windows.net/fbef9da9-667f-472c-979a-d1a1cc45d97b-1/resource/Assets0Images00018.png?sv=2017-04-17&sr=b&sig=H0GzOtB%2FWHohXOBUQTVEwnbGQl6n0prBeTm%2FfzASNfg%3D&spr=https&se=2022-06-25T05%3A06%3A26Z&sp=r",
    "6_1": "https://docserverpwaprodeus.blob.core.windows.net/fbef9da9-667f-472c-979a-d1a1cc45d97b-1/resource/Assets0Images076cafd28-65e6-47c2-b9a7-45f1a7888835.png?sv=2017-04-17&sr=b&sig=RFRlSp41rvqPWSUy72bom9Hxq36vRpA%2BadTJFZTxTT0%3D&spr=https&se=2022-06-25T05%3A06%3A26Z&sp=r",
    "6_2": "https://docserverpwaprodeus.blob.core.windows.net/fbef9da9-667f-472c-979a-d1a1cc45d97b-1/resource/Assets0Images009c8a5f3-e846-413c-9839-8ea66e8c5b67.png?sv=2017-04-17&sr=b&sig=JGhMAOM5PGH1jcbVq%2FozSt8yyR93ZUSa%2F%2BJrqhjiWD8%3D&spr=https&se=2022-06-25T05%3A06%3A26Z&sp=r",
    "7": "https://docserverpwaprodeus.blob.core.windows.net/fbef9da9-667f-472c-979a-d1a1cc45d97b-1/resource/Assets0Images00019.png?sv=2017-04-17&sr=b&sig=d3JiofTaI3mXO4rTMgwDEsSK9OOg2RdThFG90ePGpJo%3D&spr=https&se=2022-06-25T05%3A06%3A26Z&sp=r",
    "8": "https://docserverpwaprodeus.blob.core.windows.net/fbef9da9-667f-472c-979a-d1a1cc45d97b-1/resource/Assets0Images00020.png?sv=2017-04-17&sr=b&sig=Dtc63xL0lrlaLg7BklVEfThAkPHccthxhpPAiJg60Oo%3D&spr=https&se=2022-06-25T05%3A06%3A26Z&sp=r",
    "9": "https://docserverpwaprodeus.blob.core.windows.net/fbef9da9-667f-472c-979a-d1a1cc45d97b-1/resource/Assets0Images00021.png?sv=2017-04-17&sr=b&sig=KixMNQZg35dq%2FeLHfqM8voUTmWUlhwH%2FXM1xjZIe47s%3D&spr=https&se=2022-06-25T05%3A06%3A26Z&sp=r",
    "Acreditación Project": "https://docserverpwaprodeus.blob.core.windows.net/fbef9da9-667f-472c-979a-d1a1cc45d97b-1/resource/Assets0Images00026.png?sv=2017-04-17&sr=b&sig=ZYy5jHdlM3mD4FQ3rE38Bh64n%2FEawVnLmJimqwULVms%3D&spr=https&se=2022-06-25T05%3A06%3A26Z&sp=r",
    "Acreditación Project (1)": "https://docserverpwaprodeus.blob.core.windows.net/fbef9da9-667f-472c-979a-d1a1cc45d97b-1/resource/Assets0Images00023.png?sv=2017-04-17&sr=b&sig=wvT9If5kXpkhGsmOUxpCopqiN0K68y1mHK6zF0crY2A%3D&spr=https&se=2022-06-25T05%3A06%3A26Z&sp=r",
    "Acreditación Project (3)": "https://docserverpwaprodeus.blob.core.windows.net/fbef9da9-667f-472c-979a-d1a1cc45d97b-1/resource/Assets0Images00024.png?sv=2017-04-17&sr=b&sig=DMg6WbyzZ1cV%2BqbxiYfi1DI84ssgV0uLzTPhzensSPs%3D&spr=https&se=2022-06-25T05%3A06%3A26Z&sp=r",
    "Acreditación Project (4)": "https://docserverpwaprodeus.blob.core.windows.net/fbef9da9-667f-472c-979a-d1a1cc45d97b-1/resource/Assets0Images00025.png?sv=2017-04-17&sr=b&sig=7Lc8K8vfEweOC1mYAtz6h2jD%2BPt4G0Z%2FBlibqdFd79s%3D&spr=https&se=2022-06-25T05%3A06%3A26Z&sp=r",
    "Añadir un subtítulo": "https://docserverpwaprodeus.blob.core.windows.net/fbef9da9-667f-472c-979a-d1a1cc45d97b-1/resource/Assets0Images00022.jpg?sv=2017-04-17&sr=b&sig=YYgPyjA0mKVCctxhls0pX280aRP29krcWlmlgtJcdmo%3D&spr=https&se=2022-06-25T05%3A06%3A26Z&sp=r",
    "Anie Adame": "https://docserverpwaprodeus.blob.core.windows.net/fbef9da9-667f-472c-979a-d1a1cc45d97b-1/resource/Assets0Images00029.png?sv=2017-04-17&sr=b&sig=l4Pi28jkeVqzdrQECBq4KFfXt9agU1ELyQ4KjSLbsY0%3D&spr=https&se=2022-06-25T05%3A06%3A26Z&sp=r",
    "Anie Adame (1)": "https://docserverpwaprodeus.blob.core.windows.net/fbef9da9-667f-472c-979a-d1a1cc45d97b-1/resource/Assets0Images00027.png?sv=2017-04-17&sr=b&sig=CQJLwrGfAbLgVvOje3UAN4fEjcBsJrIXaon%2BTLGM13U%3D&spr=https&se=2022-06-25T05%3A06%3A26Z&sp=r",
    "Anie Adame (1)_1": "https://docserverpwaprodeus.blob.core.windows.net/fbef9da9-667f-472c-979a-d1a1cc45d97b-1/resource/Assets0Images00028.png?sv=2017-04-17&sr=b&sig=k8n00fOm5kFb5hD2e83zQ4rUNx9YziB1hTrJmCzMHwE%3D&spr=https&se=2022-06-25T05%3A06%3A26Z&sp=r",
    "Anie Adame (10)": "https://docserverpwaprodeus.blob.core.windows.net/fbef9da9-667f-472c-979a-d1a1cc45d97b-1/resource/Assets0Images051a3d7b0-9ead-4631-b262-24aa29f3c879.png?sv=2017-04-17&sr=b&sig=rgsqPounIcT441dqc4DUCMccgdihAHdIyOkA0jbtAbU%3D&spr=https&se=2022-06-25T05%3A06%3A26Z&sp=r",
    "Anie Adame (11)": "https://docserverpwaprodeus.blob.core.windows.net/fbef9da9-667f-472c-979a-d1a1cc45d97b-1/resource/Assets0Images06e9c70ce-34d9-4d9f-90f2-0744696cbdf0.png?sv=2017-04-17&sr=b&sig=48ygMB8UY9o2%2BYxoPvqLwklA5lCXVJjUXzQVV4iKI%2BA%3D&spr=https&se=2022-06-25T05%3A06%3A26Z&sp=r",
    "Anie Adame (12)": "https://docserverpwaprodeus.blob.core.windows.net/fbef9da9-667f-472c-979a-d1a1cc45d97b-1/resource/Assets0Images0a2b33d68-267b-4eca-b3e7-ae6d01ad4265.png?sv=2017-04-17&sr=b&sig=fCGSnw29wfXXa0PVeNcguZKfglGyRg2l2ETWZtrrLhk%3D&spr=https&se=2022-06-25T05%3A06%3A26Z&sp=r",
    "Anie Adame (12)_1": "https://docserverpwaprodeus.blob.core.windows.net/fbef9da9-667f-472c-979a-d1a1cc45d97b-1/resource/Assets0Images033c91d21-b0f3-43f2-b41c-32ab84f18525.png?sv=2017-04-17&sr=b&sig=y6epwwReDJ5TY%2BzrROuKfmnKYSxLFhfSzgQfNlg0xfI%3D&spr=https&se=2022-06-25T05%3A06%3A26Z&sp=r",
    "Anie Adame (12)_2": "https://docserverpwaprodeus.blob.core.windows.net/fbef9da9-667f-472c-979a-d1a1cc45d97b-1/resource/Assets0Images0f5c6335b-e7ab-4a2f-8182-407fbe53be1e.png?sv=2017-04-17&sr=b&sig=V%2FgARON%2FhlAHfZpzdgnwVcZ3zuKZ41N698SeUPMg49o%3D&spr=https&se=2022-06-25T05%3A06%3A26Z&sp=r",
    "Anie Adame (13)": "https://docserverpwaprodeus.blob.core.windows.net/fbef9da9-667f-472c-979a-d1a1cc45d97b-1/resource/Assets0Images0bfe38494-ee4e-461b-a11b-f79e7fe31642.png?sv=2017-04-17&sr=b&sig=AN0VyTRYIjDrWvbLYgnTRCtcE%2Bffp8aPlHtwWqR4Ndg%3D&spr=https&se=2022-06-25T05%3A06%3A26Z&sp=r",
    "Anie Adame (13)_1": "https://docserverpwaprodeus.blob.core.windows.net/fbef9da9-667f-472c-979a-d1a1cc45d97b-1/resource/Assets0Images04ddc87ee-7e79-4fe8-8341-5c783afae2a5.png?sv=2017-04-17&sr=b&sig=tLMl6AOlOxTcumGTvmZgEk5CNnoumduzti2XV8S4A8s%3D&spr=https&se=2022-06-25T05%3A06%3A26Z&sp=r",
    "Anie Adame (14)": "https://docserverpwaprodeus.blob.core.windows.net/fbef9da9-667f-472c-979a-d1a1cc45d97b-1/resource/Assets0Images0618a924d-a515-4db6-8e55-bc9ce146cc61.png?sv=2017-04-17&sr=b&sig=cuc0a5rzzrx2T0fztR0KASYLXT4xwG95RHTVyk8OZ9I%3D&spr=https&se=2022-06-25T05%3A06%3A26Z&sp=r",
    "Anie Adame (14)_1": "https://docserverpwaprodeus.blob.core.windows.net/fbef9da9-667f-472c-979a-d1a1cc45d97b-1/resource/Assets0Images03ccbe5a2-3d21-41bf-80e0-4b6d21fd47cf.png?sv=2017-04-17&sr=b&sig=9sfTt%2Flu6tkiQIDlekpw8lCRIYs3PWCOEF6McTcibJE%3D&spr=https&se=2022-06-25T05%3A06%3A26Z&sp=r",
    "Anie Adame (15)": "https://docserverpwaprodeus.blob.core.windows.net/fbef9da9-667f-472c-979a-d1a1cc45d97b-1/resource/1f633550-832c-4b58-8947-913942e0a75b.png?sv=2017-04-17&sr=b&sig=mgzoFnXQOHUewI3n9cKM49KyBBtgR7hz4csyZmi5Y5E%3D&spr=https&se=2022-06-25T05%3A26%3A34Z&sp=r",
    "Anie Adame (15)_1": "https://docserverpwaprodeus.blob.core.windows.net/fbef9da9-667f-472c-979a-d1a1cc45d97b-1/resource/dbdf58f5-041d-4e54-b6b0-c41f395a6a43.png?sv=2017-04-17&sr=b&sig=kB77HmNc1%2FcXTi9nAReNdg7hcIoJNHz5%2FjjSE7hPrm8%3D&spr=https&se=2022-06-25T05%3A26%3A50Z&sp=r",
    "Anie Adame (16)": "https://docserverpwaprodeus.blob.core.windows.net/fbef9da9-667f-472c-979a-d1a1cc45d97b-1/resource/e7fa8cd4-7945-402c-bff6-64c4f5d4f0f8.png?sv=2017-04-17&sr=b&sig=qbHUehMr60oskqd3mnpPzHn4VEsAOwIwMUYJY3ceD5Y%3D&spr=https&se=2022-06-25T07%3A38%3A19Z&sp=r",
    "Anie Adame (5)": "https://docserverpwaprodeus.blob.core.windows.net/fbef9da9-667f-472c-979a-d1a1cc45d97b-1/resource/Assets0Images093d69d76-a1b8-44e0-9c9a-d009f6d41f2c.png?sv=2017-04-17&sr=b&sig=v8TdPPCbmN9zU7laBS0p8QytVBLOFRqZLWIHbdpSiQ8%3D&spr=https&se=2022-06-25T05%3A06%3A26Z&sp=r",
    "Anie Adame (6)": "https://docserverpwaprodeus.blob.core.windows.net/fbef9da9-667f-472c-979a-d1a1cc45d97b-1/resource/Assets0Images035eb6dff-9031-4eff-bafc-e0364c79f104.png?sv=2017-04-17&sr=b&sig=RzVX4feHSYUExYtIjWydbndJLr4QjowJquK6Chrl134%3D&spr=https&se=2022-06-25T05%3A06%3A26Z&sp=r",
    "Anie Adame (7)": "https://docserverpwaprodeus.blob.core.windows.net/fbef9da9-667f-472c-979a-d1a1cc45d97b-1/resource/Assets0Images05f337746-8111-448b-8f78-c88ccd59ffc7.png?sv=2017-04-17&sr=b&sig=ewf6RlXUthQIcFg%2BtJoCAfool1WDQ4YeEXyCHvxZZ2U%3D&spr=https&se=2022-06-25T05%3A06%3A26Z&sp=r",
    "Anie Adame (8)": "https://docserverpwaprodeus.blob.core.windows.net/fbef9da9-667f-472c-979a-d1a1cc45d97b-1/resource/Assets0Images0ebf33901-066e-4780-b837-3891ba6a7308.png?sv=2017-04-17&sr=b&sig=beQ%2B25SV4UgR5kD2yTBLsl%2F7a%2FkE0A7Kxy2hT0PXvrY%3D&spr=https&se=2022-06-25T05%3A06%3A26Z&sp=r",
    "Anie Adame (8)_1": "https://docserverpwaprodeus.blob.core.windows.net/fbef9da9-667f-472c-979a-d1a1cc45d97b-1/resource/Assets0Images019bebd3e-790b-44a6-ba74-655fc518fc8f.png?sv=2017-04-17&sr=b&sig=3TDKO72Xkr%2FfVi1cy77lN3iBZ%2BNJ319ZuUBdVCa0fYU%3D&spr=https&se=2022-06-25T05%3A06%3A26Z&sp=r",
    "Anie Adame (9)": "https://docserverpwaprodeus.blob.core.windows.net/fbef9da9-667f-472c-979a-d1a1cc45d97b-1/resource/Assets0Images0be310e24-d726-4fa9-8bdf-79ef1517ecd1.png?sv=2017-04-17&sr=b&sig=lUPFlcb8aoyzdtDG%2FqBnQbud7QlRQVp1pAy9rfz2UsQ%3D&spr=https&se=2022-06-25T05%3A06%3A26Z&sp=r",
    "Avatar Power apps": "https://docserverpwaprodeus.blob.core.windows.net/fbef9da9-667f-472c-979a-d1a1cc45d97b-1/resource/Assets0Images00030.png?sv=2017-04-17&sr=b&sig=sCEVuYguXpbh7B%2BLi46WYQfMZkxjr3QqZjuGdaCgWXA%3D&spr=https&se=2022-06-25T05%3A06%3A26Z&sp=r",
    "chat": "https://docserverpwaprodeus.blob.core.windows.net/fbef9da9-667f-472c-979a-d1a1cc45d97b-1/resource/Assets0Images00031.png?sv=2017-04-17&sr=b&sig=M8xba1TdYuyXavX%2FCKpQW6KPoM364m8ULoYpxHpOfMw%3D&spr=https&se=2022-06-25T05%3A06%3A26Z&sp=r",
    "Cielo_nublado": "https://docserverpwaprodeus.blob.core.windows.net/fbef9da9-667f-472c-979a-d1a1cc45d97b-1/resource/Assets0Images00032.jpg?sv=2017-04-17&sr=b&sig=Z%2BN9vMVzM7mWNpeXje82%2FJxaxabTIVvjl6NYrR0Msk8%3D&spr=https&se=2022-06-25T05%3A06%3A26Z&sp=r",
    "difuminado 2": "https://docserverpwaprodeus.blob.core.windows.net/fbef9da9-667f-472c-979a-d1a1cc45d97b-1/resource/Assets0Images00033.jpg?sv=2017-04-17&sr=b&sig=ufVRrocGdlru9ODuFucslieOZVCBC7eK1B2OL080Uso%3D&spr=https&se=2022-06-25T05%3A06%3A26Z&sp=r",
    "Diseño sin título (1)": "https://docserverpwaprodeus.blob.core.windows.net/fbef9da9-667f-472c-979a-d1a1cc45d97b-1/resource/Assets0Images0871675c1-5614-4827-b2f1-5e9d06381a62.png?sv=2017-04-17&sr=b&sig=nPAjj3FBpcFZF5sKXPYo9rW3ZOVo6XKD2N8NQGy4Mik%3D&spr=https&se=2022-06-25T05%3A06%3A26Z&sp=r",
    "Diseño sin título (2)": "https://docserverpwaprodeus.blob.core.windows.net/fbef9da9-667f-472c-979a-d1a1cc45d97b-1/resource/Assets0Images0b773bfdf-abac-44c4-879c-b735bb5cbbf2.png?sv=2017-04-17&sr=b&sig=QhYg1lKJHzvTTJUMsp%2Bu6qcsjBDh03MBorpDuYTsrag%3D&spr=https&se=2022-06-25T05%3A06%3A26Z&sp=r",
    "Diseño sin título (3)": "https://docserverpwaprodeus.blob.core.windows.net/fbef9da9-667f-472c-979a-d1a1cc45d97b-1/resource/Assets0Images07ffbf2ee-22a5-4ce2-9df4-9728ec408e92.png?sv=2017-04-17&sr=b&sig=QeRvyWh5Uej4ypwte8amm80jwIkg5pgOyo3wu9bhoPw%3D&spr=https&se=2022-06-25T05%3A06%3A26Z&sp=r",
    "Diseño sin título (3)_1": "https://docserverpwaprodeus.blob.core.windows.net/fbef9da9-667f-472c-979a-d1a1cc45d97b-1/resource/Assets0Images08bae8a98-64c4-4353-a8f0-6a11805d78fa.png?sv=2017-04-17&sr=b&sig=vcUhTe7frmHdvyOKcZY%2FKSnCbRdCxPstu%2BsA7HsxNsE%3D&spr=https&se=2022-06-25T05%3A06%3A26Z&sp=r",
    "Diseño sin título (4)": "https://docserverpwaprodeus.blob.core.windows.net/fbef9da9-667f-472c-979a-d1a1cc45d97b-1/resource/Assets0Images004d4c893-af18-4e56-a177-d739ab90d002.png?sv=2017-04-17&sr=b&sig=CJAWXTp%2FBrOI3dKpMUvs9zf1R1FZ1OjH8QH8Am9dToE%3D&spr=https&se=2022-06-25T05%3A06%3A26Z&sp=r",
    "Diseño sin título (5)": "https://docserverpwaprodeus.blob.core.windows.net/fbef9da9-667f-472c-979a-d1a1cc45d97b-1/resource/Assets0Images0cc77b009-bca6-4ef5-90ab-8241d88ee0fa.png?sv=2017-04-17&sr=b&sig=W0%2FQB0nrL7E1z0rUSk13kpnHzveDVXbcZuMPcW956As%3D&spr=https&se=2022-06-25T05%3A06%3A26Z&sp=r",
    "Diseño sin título (6)": "https://docserverpwaprodeus.blob.core.windows.net/fbef9da9-667f-472c-979a-d1a1cc45d97b-1/resource/8eb57aa0-1792-4eea-933b-a85fbaa0e9b1.png?sv=2017-04-17&sr=b&sig=DW7dt0QNLH1FYLhw%2FR%2FcLuI%2FMRpqTeWBQ9dIyzjVKUY%3D&spr=https&se=2022-06-25T05%3A28%3A58Z&sp=r",
    "Diseño sin título (7)": "https://docserverpwaprodeus.blob.core.windows.net/fbef9da9-667f-472c-979a-d1a1cc45d97b-1/resource/57c41c2d-35c2-4ec9-b26d-b77963d26b01.png?sv=2017-04-17&sr=b&sig=mDpMSQjlHxoIveF712Lv0qX1zaecYYau7JCoMVmvcl8%3D&spr=https&se=2022-06-25T05%3A32%3A46Z&sp=r",
    "Diseño sin título (8)": "https://docserverpwaprodeus.blob.core.windows.net/fbef9da9-667f-472c-979a-d1a1cc45d97b-1/resource/069885a2-a75c-4976-8125-cc68dd7c71d7.png?sv=2017-04-17&sr=b&sig=dWt%2BtIKFW%2B4i6nPtvc5kujpaJ1T5r%2F%2BvBBexjS%2FhLMA%3D&spr=https&se=2022-06-25T07%3A54%3A39Z&sp=r",
    "download": "https://docserverpwaprodeus.blob.core.windows.net/fbef9da9-667f-472c-979a-d1a1cc45d97b-1/resource/Assets0Images00034.png?sv=2017-04-17&sr=b&sig=qB2l4f1upQMfUe0I7pagXJb%2B%2FE6o%2FaTobfpXIgznC7U%3D&spr=https&se=2022-06-25T05%3A06%3A26Z&sp=r",
    "fondo": "https://docserverpwaprodeus.blob.core.windows.net/fbef9da9-667f-472c-979a-d1a1cc45d97b-1/resource/Assets0Images00035.png?sv=2017-04-17&sr=b&sig=Np%2FkGqDkerhfiWL8eSVXFBmqCHtIZ2aVUtbw3Kc0b8A%3D&spr=https&se=2022-06-25T05%3A06%3A26Z&sp=r",
    "Logo Acrediitación Azul": "https://docserverpwaprodeus.blob.core.windows.net/fbef9da9-667f-472c-979a-d1a1cc45d97b-1/resource/Assets0Images00036.png?sv=2017-04-17&sr=b&sig=u%2FBCPcXSeluIuMdkEvuAnLXHudsetSU9nak14iA2dC4%3D&spr=https&se=2022-06-25T05%3A06%3A26Z&sp=r",
    "Logo Acreditación": "https://docserverpwaprodeus.blob.core.windows.net/fbef9da9-667f-472c-979a-d1a1cc45d97b-1/resource/Assets0Images00037.png?sv=2017-04-17&sr=b&sig=DgXkx9xCJBdTCTTFof1HZUn7zGQaSrbAT6lf9nczdrg%3D&spr=https&se=2022-06-25T05%3A06%3A26Z&sp=r",
    "master": "https://docserverpwaprodeus.blob.core.windows.net/fbef9da9-667f-472c-979a-d1a1cc45d97b-1/resource/Assets0Images00038.jpg?sv=2017-04-17&sr=b&sig=H1MDcnmgn6OFIAzH%2F4LHmbTSahGk%2FCFJAWTE6nmkMJE%3D&spr=https&se=2022-06-25T05%3A06%3A26Z&sp=r",
    "Negro Sencillo Evento Deportivo Póster": "https://docserverpwaprodeus.blob.core.windows.net/fbef9da9-667f-472c-979a-d1a1cc45d97b-1/resource/Assets0Images00039.jpg?sv=2017-04-17&sr=b&sig=vqVyGyxkiwMtjHigkr4hVzGGmnFHusoO4oFyTBipkLE%3D&spr=https&se=2022-06-25T05%3A06%3A26Z&sp=r",
    "Notification Message": "https://docserverpwaprodeus.blob.core.windows.net/fbef9da9-667f-472c-979a-d1a1cc45d97b-1/resource/Assets0Images00040.png?sv=2017-04-17&sr=b&sig=ToNKZefjgF45IuvZ5xYlo2B5HL555%2FmcAoQ5MWpdz58%3D&spr=https&se=2022-06-25T05%3A06%3A26Z&sp=r",
    "Zulu (2)": "https://docserverpwaprodeus.blob.core.windows.net/fbef9da9-667f-472c-979a-d1a1cc45d97b-1/resource/92121302-a851-4d19-9e4a-25567ea62658.png?sv=2017-04-17&sr=b&sig=cGIgGImpC8VbAvuJVMRqbVRSCMUCdE16J3b4%2FfqYSHQ%3D&spr=https&se=2022-06-25T07%3A10%3A57Z&sp=r",
    "Zulu (3)": "https://docserverpwaprodeus.blob.core.windows.net/fbef9da9-667f-472c-979a-d1a1cc45d97b-1/resource/e5721d56-9d03-463d-a72f-af612c3b5d3f.png?sv=2017-04-17&sr=b&sig=jONVokx%2BBKfMyDQp4ggLg%2F3CajTpL0FScp91VpRPH1o%3D&spr=https&se=2022-06-25T07%3A17%3A00Z&sp=r",
    "Zulu (4)": "https://docserverpwaprodeus.blob.core.windows.net/fbef9da9-667f-472c-979a-d1a1cc45d97b-1/resource/bfc95d62-4f56-4eaa-8fb9-c1dcb1eeb5ad.png?sv=2017-04-17&sr=b&sig=ZtzHg7RmMPGYYjHtD2ArFe2A2hs82GIbMGYvEZitXJg%3D&spr=https&se=2022-06-25T07%3A44%3A22Z&sp=r",
    "Zulu (5)": "https://docserverpwaprodeus.blob.core.windows.net/fbef9da9-667f-472c-979a-d1a1cc45d97b-1/resource/6a4b0c4b-a928-4bb6-b8d1-af063b61c7ef.png?sv=2017-04-17&sr=b&sig=NZ8NGQ3QO18RKkFyQl%2BWGr3NLeekgEW%2FkaC7jSOAl3w%3D&spr=https&se=2022-06-25T07%3A42%3A08Z&sp=r",
    "Zulu (6)": "https://docserverpwaprodeus.blob.core.windows.net/fbef9da9-667f-472c-979a-d1a1cc45d97b-1/resource/69c88f5c-f9ac-4d36-a87d-a9808f6d8a1a.png?sv=2017-04-17&sr=b&sig=ZzRW9WIpeJ4KS8d4a972Q2iHHMd%2Fhe8JjU8CpDxymyM%3D&spr=https&se=2022-06-25T07%3A43%3A32Z&sp=r",
    "Zulu (7)": "https://docserverpwaprodeus.blob.core.windows.net/fbef9da9-667f-472c-979a-d1a1cc45d97b-1/resource/9e82a33b-78c0-4fae-bdb8-a057385d0f16.png?sv=2017-04-17&sr=b&sig=4EszsvpnoLeS%2FJmuICAo8r29HoPYAhR6vOA5PX4WHEo%3D&spr=https&se=2022-06-25T07%3A51%3A40Z&sp=r",
    "Zulu (7)_1": "https://docserverpwaprodeus.blob.core.windows.net/fbef9da9-667f-472c-979a-d1a1cc45d97b-1/resource/5fc432e4-86de-4e64-9ca6-6d185c1671ab.png?sv=2017-04-17&sr=b&sig=cg6JuV%2B7GbqQ1aAya3NgHcqE6qa4ReAIbVvuzJ55q8w%3D&spr=https&se=2022-06-25T08%3A00%3A26Z&sp=r",
    "Zulu (8)": "https://docserverpwaprodeus.blob.core.windows.net/fbef9da9-667f-472c-979a-d1a1cc45d97b-1/resource/6652dee7-37e8-4efd-9944-667186b6aba8.png?sv=2017-04-17&sr=b&sig=pq89hh6hMzUKjX3YM7ul3h1wo9kJgHyGtfaQfCyCcK8%3D&spr=https&se=2022-06-25T07%3A52%3A00Z&sp=r",
    "Zulu (8)_1": "https://docserverpwaprodeus.blob.core.windows.net/fbef9da9-667f-472c-979a-d1a1cc45d97b-1/resource/78e1dc3b-92ae-4ae7-923f-8f28f22f6192.png?sv=2017-04-17&sr=b&sig=LGI7pKz5L7IUCIdhE8hpaXQjap9A%2FaZfeZv7CSeikf8%3D&spr=https&se=2022-06-25T07%3A59%3A48Z&sp=r",
    "Zulu (9)": "https://docserverpwaprodeus.blob.core.windows.net/fbef9da9-667f-472c-979a-d1a1cc45d97b-1/resource/ee7590dc-d7eb-47fe-b681-0eeb2a8cf08c.png?sv=2017-04-17&sr=b&sig=ZGqbbOpjynJ34iESCPbuwKp61%2FmEOKYOWGZh9bAo6Eg%3D&spr=https&se=2022-06-25T07%3A52%3A21Z&sp=r",
    "Zulu (9)_1": "https://docserverpwaprodeus.blob.core.windows.net/fbef9da9-667f-472c-979a-d1a1cc45d97b-1/resource/b49065f9-af3d-471b-b046-401bc3276316.png?sv=2017-04-17&sr=b&sig=rbl5qCthg%2BHyCIfTNVfCzBT2DZPTwtYamGfxP6ANTdQ%3D&spr=https&se=2022-06-25T08%3A00%3A09Z&sp=r",
    "Zulu_presentación-removebg-preview": "https://docserverpwaprodeus.blob.core.windows.net/fbef9da9-667f-472c-979a-d1a1cc45d97b-1/resource/Assets0Images00041.png?sv=2017-04-17&sr=b&sig=lla3jDSn0jiUJiNnNpMDgvy5G7HSo5OGc5%2FNAEwFLy4%3D&spr=https&se=2022-06-25T05%3A06%3A26Z&sp=r"
  },
  "OrderComponentMetadata": {},
  "OrderComponentTemplate": {},
  "OrderDataSource": {
    "43b0dc67-68af-47ae-9a9c-9e69d396ba3e": 6,
    "App Flow": 0,
    "CustomGallerySample": 3,
    "EspaciodeescuchaChat": 1,
    "RadioSample": 4,
    "SendButtom": 2,
    "ZULU": 5
  },
  "OrderGroupControls": {},
  "OrderPcfTemplate": {},
  "OrderTemplate": {},
  "OrderXMLTemplate": {
    "button": 6,
    "circle": 5,
    "datepicker": 8,
    "icon": 1,
    "image": 0,
    "label": 2,
    "rectangle": 4,
    "text": 7,
    "toggleSwitch": 3
  },
  "PublishOrderIndices": {
    "App": 0,
    "Background Music": 0,
    "Button2": 10,
    "Button3": 286,
    "Button4": 7,
    "Button4_1": 255,
    "Button4_2": 296,
    "Button6": 99,
    "Button6_1": 68,
    "Button6_10": 97,
    "Button6_11": 263,
    "Button6_12": 147,
    "Button6_13": 150,
    "Button6_14": 152,
    "Button6_15": 158,
    "Button6_16": 155,
    "Button6_17": 160,
    "Button6_18": 163,
    "Button6_19": 160,
    "Button6_2": 121,
    "Button6_20": 160,
    "Button6_21": 163,
    "Button6_3": 124,
    "Button6_4": 129,
    "Button6_5": 132,
    "Button6_6": 137,
    "Button6_7": 140,
    "Button6_8": 250,
    "Button6_9": 13,
    "Chatbot": 2,
    "Circle1": 8,
    "Circle1_1": 6,
    "Circle1_2": 11,
    "Circle1_3": 9,
    "Circle1_4": 104,
    "Circle1_5": 118,
    "Circle1_6": 256,
    "Circle1_7": 254,
    "Circle1_8": 297,
    "Circle1_9": 295,
    "Circle2": 111,
    "Circle2_1": 134,
    "Circle3": 235,
    "Circle3_1": 197,
    "Circle3_2": 173,
    "Circle3_3": 209,
    "Circle3_4": 223,
    "Circle3_5": 185,
    "Circle4": 180,
    "Circle4_1": 192,
    "Circle4_2": 204,
    "Circle4_3": 219,
    "Circle4_4": 230,
    "Circle4_5": 243,
    "Circle4_6": 288,
    "Circle4_7": 290,
    "Circle4_8": 292,
    "Emotions_1": 25,
    "Icon1": 17,
    "Icon1_1": 18,
    "Icon1_10": 27,
    "Icon1_11": 30,
    "Icon1_12": 31,
    "Icon1_13": 33,
    "Icon1_14": 32,
    "Icon1_15": 34,
    "Icon1_16": 35,
    "Icon1_17": 36,
    "Icon1_18": 37,
    "Icon1_19": 38,
    "Icon1_2": 20,
    "Icon1_20": 39,
    "Icon1_21": 40,
    "Icon1_22": 43,
    "Icon1_23": 44,
    "Icon1_24": 46,
    "Icon1_25": 45,
    "Icon1_26": 47,
    "Icon1_27": 48,
    "Icon1_28": 49,
    "Icon1_29": 50,
    "Icon1_3": 19,
    "Icon1_30": 51,
    "Icon1_31": 52,
    "Icon1_32": 53,
    "Icon1_33": 56,
    "Icon1_34": 57,
    "Icon1_35": 59,
    "Icon1_36": 58,
    "Icon1_37": 60,
    "Icon1_38": 61,
    "Icon1_39": 62,
    "Icon1_4": 21,
    "Icon1_40": 63,
    "Icon1_41": 64,
    "Icon1_42": 65,
    "Icon1_43": 66,
    "Icon1_44": 73,
    "Icon1_45": 74,
    "Icon1_46": 76,
    "Icon1_47": 75,
    "Icon1_48": 77,
    "Icon1_49": 78,
    "Icon1_5": 22,
    "Icon1_50": 79,
    "Icon1_51": 80,
    "Icon1_52": 81,
    "Icon1_53": 82,
    "Icon1_54": 83,
    "Icon1_55": 86,
    "Icon1_56": 87,
    "Icon1_57": 89,
    "Icon1_58": 88,
    "Icon1_59": 90,
    "Icon1_6": 23,
    "Icon1_60": 91,
    "Icon1_61": 92,
    "Icon1_62": 93,
    "Icon1_63": 94,
    "Icon1_64": 95,
    "Icon1_65": 96,
    "Icon1_7": 24,
    "Icon1_8": 25,
    "Icon1_9": 26,
    "Icon2_2": 210,
    "Icon3": 101,
    "Icon5": 170,
    "Icon5_1": 182,
    "Icon5_10": 311,
    "Icon5_11": 323,
    "Icon5_12": 251,
    "Icon5_13": 257,
    "Icon5_14": 265,
    "Icon5_2": 194,
    "Icon5_3": 206,
    "Icon5_4": 220,
    "Icon5_5": 232,
    "Icon5_6": 245,
    "Icon5_7": 293,
    "Icon5_8": 143,
    "Icon5_9": 298,
    "Icon6": 249,
    "Icon7": 248,
    "Icon8": 264,
    "Icon9": 102,
    "Image1": 5,
    "Image10": 4,
    "Image11": 3,
    "Image11_1": 184,
    "Image12_10": 179,
    "Image12_11": 191,
    "Image12_12": 217,
    "Image12_13": 229,
    "Image12_14": 241,
    "Image12_7": 196,
    "Image12_9": 202,
    "Image13_1": 234,
    "Image13_10": 205,
    "Image13_11": 231,
    "Image13_12": 244,
    "Image13_13": 242,
    "Image13_6": 181,
    "Image13_7": 218,
    "Image13_9": 193,
    "Image15": 141,
    "Image15_10": 203,
    "Image15_11": 226,
    "Image15_12": 240,
    "Image15_5": 177,
    "Image15_6": 215,
    "Image15_7": 222,
    "Image15_9": 190,
    "Image16": 246,
    "Image17": 142,
    "Image17_1": 148,
    "Image17_2": 154,
    "Image17_3": 161,
    "Image17_4": 166,
    "Image19": 146,
    "Image19_1": 153,
    "Image19_2": 159,
    "Image19_3": 165,
    "Image21": 253,
    "Image22": 168,
    "Image24": 300,
    "Image24_1": 310,
    "Image25": 304,
    "Image25_1": 316,
    "Image26": 305,
    "Image26_1": 317,
    "Image27": 306,
    "Image27_1": 318,
    "Image29": 149,
    "Image29_1": 156,
    "Image29_2": 145,
    "Image29_3": 164,
    "Image3": 103,
    "Image3_1": 12,
    "Image3_2": 1,
    "Image3_3": 69,
    "Image3_4": 117,
    "Image3_5": 151,
    "Image3_6": 157,
    "Image3_7": 162,
    "Image3_8": 167,
    "Image4": 115,
    "Image5": 326,
    "Image5_2": 279,
    "Image6": 116,
    "Image6_6": 287,
    "Image6_7": 289,
    "Image6_8": 291,
    "Image7": 327,
    "Image7_10": 200,
    "Image7_11": 214,
    "Image7_12": 227,
    "Image7_13": 238,
    "Image7_7": 176,
    "Image7_8": 172,
    "Image7_9": 189,
    "Image8_10": 199,
    "Image8_11": 225,
    "Image8_12": 237,
    "Image8_5": 175,
    "Image8_6": 213,
    "Image8_7": 208,
    "Image8_8": 212,
    "Image8_9": 187,
    "Image9": 2,
    "Image9_1": 144,
    "Image9_10": 239,
    "Image9_5": 178,
    "Image9_6": 216,
    "Image9_7": 188,
    "Image9_8": 201,
    "Image9_9": 228,
    "Label1": 282,
    "Label12": 0,
    "Label3": 280,
    "Label4": 284,
    "Label5": 233,
    "Label5_1": 236,
    "Label5_10": 84,
    "Label5_11": 98,
    "Label5_12": 221,
    "Label5_13": 207,
    "Label5_14": 171,
    "Label5_15": 174,
    "Label5_16": 198,
    "Label5_17": 186,
    "Label5_18": 224,
    "Label5_19": 211,
    "Label5_2": 195,
    "Label5_3": 183,
    "Label5_4": 41,
    "Label5_5": 54,
    "Label5_6": 15,
    "Label5_7": 28,
    "Label5_8": 67,
    "Label5_9": 71,
    "Label7": 119,
    "Label7_1": 14,
    "Label7_10": 267,
    "Label7_11": 270,
    "Label7_12": 269,
    "Label7_13": 271,
    "Label7_14": 273,
    "Label7_15": 274,
    "Label7_16": 275,
    "Label7_17": 277,
    "Label7_18": 278,
    "Label7_2": 70,
    "Label7_3": 247,
    "Label7_4": 252,
    "Label7_5": 258,
    "Label7_6": 259,
    "Label7_7": 260,
    "Label7_8": 262,
    "Label7_9": 266,
    "Label8": 105,
    "Label8_1": 106,
    "Label8_10": 133,
    "Label8_11": 138,
    "Label8_12": 294,
    "Label8_13": 322,
    "Label8_14": 302,
    "Label8_15": 303,
    "Label8_16": 307,
    "Label8_17": 308,
    "Label8_18": 309,
    "Label8_19": 314,
    "Label8_2": 108,
    "Label8_20": 315,
    "Label8_21": 319,
    "Label8_22": 320,
    "Label8_23": 321,
    "Label8_24": 328,
    "Label8_25": 299,
    "Label8_26": 312,
    "Label8_27": 324,
    "Label8_3": 107,
    "Label8_4": 110,
    "Label8_5": 113,
    "Label8_6": 122,
    "Label8_7": 125,
    "Label8_8": 128,
    "Label8_9": 127,
    "Portal Screen": 40,
    "Portal Screen_1": 48,
    "Portal Screen_2": 0,
    "Presentation Screen": 57,
    "Profile Screen_1": 65,
    "Profile Screen_2": 0,
    "Rectangle1_14": 123,
    "Rectangle1_15": 126,
    "Rectangle1_16": 130,
    "Rectangle1_17": 136,
    "Rectangle1_18": 139,
    "Rectangle1_3": 109,
    "Rectangle1_4": 112,
    "Rectangle1_5": 131,
    "Rectangle1_6": 135,
    "Rectangle1_7": 120,
    "Rectangle4": 100,
    "Rectangle4_1": 114,
    "Schedule_1": 0,
    "Schedule_2": 0,
    "Schedule_3": 0,
    "Schedule_4": 0,
    "Special Break_1": 0,
    "Special Break_2": 0,
    "Special Break_3": 0,
    "Special Break_4": 0,
    "Special Break_5": 0,
    "Special Break_6": 0,
    "Special Break_7": 0,
    "Special Break_8": 0,
    "Special Break_9": 0,
    "TextInput5_10": 72,
    "TextInput5_11": 85,
    "TextInput5_12": 261,
    "TextInput5_4": 16,
    "TextInput5_5": 169,
    "TextInput5_7": 29,
    "TextInput5_8": 42,
    "TextInput5_9": 55,
    "To relax your mind_1_Serene": 5,
    "To relax your mind_2_Anger": 0,
    "To relax your mind_3_Surprised": 0,
    "To relax your mind_4_Happy": 0,
    "To relax your mind_5_Insecure": 0,
    "To relax your mind_6_Sad": 0,
    "Toggle1": 268,
    "Toggle1_1": 272,
    "Toggle1_2": 276,
    "Toggle2": 301,
    "Toggle2_1": 325,
    "Toggle2_2": 313,
    "txtdate": 283,
    "txtHowdoyoufeel": 285,
    "txtName": 281
  },
  "ResourcesJsonIndices": {
    "Image-1": 1,
    "Image-10": 3,
    "Image-10-removebg-preview": 2,
    "Image-11": 4,
    "Image-12": 6,
    "Image-12-removebg-preview": 5,
    "Image-13": 8,
    "Image-13-removebg-preview": 7,
    "Image-14": 10,
    "Image-14-removebg-preview": 9,
    "Image-15": 12,
    "Image-15-removebg-preview": 11,
    "Image-17": 13,
    "Image-19": 14,
    "Image-2": 15,
    "Image-2_1": 47,
    "Image-22": 53,
    "Image-22_1": 59,
    "Image-23": 58,
    "Image-23_1": 67,
    "Image-23_2": 68,
    "Image-24": 56,
    "Image-24_1": 57,
    "Image-24_2": 69,
    "Image-25": 70,
    "Image-26": 55,
    "Image-26_1": 71,
    "Image-26_2": 72,
    "Image-27": 54,
    "Image-27_1": 73,
    "Image-28": 74,
    "Image-3": 16,
    "Image-3_1": 48,
    "Image-4": 17,
    "Image-4_1": 49,
    "Image-4_2": 78,
    "Image-5": 50,
    "Image-5_1": 79,
    "Image-6": 18,
    "Image-6_1": 51,
    "Image-6_2": 80,
    "Image-7": 19,
    "Image-8": 20,
    "Image-9": 21,
    "Image-Acreditación Project": 26,
    "Image-Acreditación Project (1)": 23,
    "Image-Acreditación Project (3)": 24,
    "Image-Acreditación Project (4)": 25,
    "Image-Añadir un subtítulo": 22,
    "Image-Anie Adame": 29,
    "Image-Anie Adame (1)": 27,
    "Image-Anie Adame (1)_1": 28,
    "Image-Anie Adame (10)": 61,
    "Image-Anie Adame (11)": 66,
    "Image-Anie Adame (12)": 75,
    "Image-Anie Adame (12)_1": 76,
    "Image-Anie Adame (12)_2": 82,
    "Image-Anie Adame (13)": 81,
    "Image-Anie Adame (13)_1": 83,
    "Image-Anie Adame (14)": 84,
    "Image-Anie Adame (14)_1": 85,
    "Image-Anie Adame (15)": 86,
    "Image-Anie Adame (15)_1": 87,
    "Image-Anie Adame (16)": 92,
    "Image-Anie Adame (5)": 42,
    "Image-Anie Adame (6)": 43,
    "Image-Anie Adame (7)": 44,
    "Image-Anie Adame (8)": 46,
    "Image-Anie Adame (8)_1": 52,
    "Image-Anie Adame (9)": 60,
    "Image-Avatar Power apps": 30,
    "Image-chat": 31,
    "Image-Cielo_nublado": 32,
    "Image-difuminado 2": 33,
    "Image-Diseño sin título (1)": 45,
    "Image-Diseño sin título (2)": 62,
    "Image-Diseño sin título (3)": 63,
    "Image-Diseño sin título (3)_1": 65,
    "Image-Diseño sin título (4)": 64,
    "Image-Diseño sin título (5)": 77,
    "Image-Diseño sin título (6)": 88,
    "Image-Diseño sin título (7)": 89,
    "Image-Diseño sin título (8)": 99,
    "Image-download": 34,
    "Image-fondo": 35,
    "Image-Logo Acrediitación Azul": 36,
    "Image-Logo Acreditación": 37,
    "Image-master": 38,
    "Image-Negro Sencillo Evento Deportivo Póster": 39,
    "Image-Notification Message": 40,
    "Image-SampleImage": 0,
    "Image-Zulu (2)": 90,
    "Image-Zulu (3)": 91,
    "Image-Zulu (4)": 95,
    "Image-Zulu (5)": 93,
    "Image-Zulu (6)": 94,
    "Image-Zulu (7)": 96,
    "Image-Zulu (7)_1": 102,
    "Image-Zulu (8)": 97,
    "Image-Zulu (8)_1": 100,
    "Image-Zulu (9)": 98,
    "Image-Zulu (9)_1": 101,
    "Image-Zulu_presentación-removebg-preview": 41
  },
  "RuleScreenIdWithoutScreen": {},
  "TemplateVersions": {},
  "VolatileProperties": {
    "AnalysisLoadTime": 1.4625556,
    "ControlCount": {
      "button": 28,
      "circle": 27,
      "datepicker": 1,
      "icon": 89,
      "image": 89,
      "label": 72,
      "powerbi": 1,
      "rectangle": 12,
      "screen": 27,
      "text": 10,
      "toggleSwitch": 6
    },
    "DeserializationLoadTime": 12.1936147,
    "ErrorCount": 0
  },
  "WasLocalDatabaseReferencesEmpty": false
}